slims_lisp/__init__.py
slims_lisp/__main__.py
slims_lisp/slims.py
slims_lisp-0.2.0.dist-info/LICENSE
slims_lisp-0.2.0.dist-info/METADATA
slims_lisp-0.2.0.dist-info/WHEEL
slims_lisp-0.2.0.dist-info/entry_points.txt
slims_lisp-0.2.0.dist-info/top_level.txt
slims_lisp-0.2.0.dist-info/RECORD
