Metadata-Version: 2.1
Name: slims-lisp
Version: 0.2.0
Summary: A high-level CLI for SlIMS REST API
Home-page: https://github.com/auwerxlab/slims-lisp-python-api
Author: Laboratory of Integrative System Physiology (LISP) at EPFL
Author-email: alexis.rapin@epfl.ch
License: Apache License 2.0
Download-URL: https://github.com/auwerxlab/slims-lisp-python-api/archive/v0.2.0.tar.gz
Platform: UNKNOWN
Requires-Python: >=3.5.2
Requires-Dist: click (>=7.0)
Requires-Dist: requests (>=2.22.0)
Requires-Dist: datetime (>=4.3)
